{
  "fetched_utc": "2026-06-05T19:34:11Z",
  "source": "CoinMarketCap web data-api (cryptocurrency/detail statistics)",
  "note": "CURRENT/live FDV/MC/supply snapshot",
  "tokens": {
    "2Z": {
      "price": 0.06924040401544415,
      "fdv_usd": 692404040.15,
      "mcap_usd": 240362350.21,
      "circulating_supply": 3471417500.0,
      "total_supply": 9998385316.2,
      "max_supply": 10000000000.0,
      "date_launched": "2025-09-30T00:00:00.000Z",
      "slug": "doublezero",
      "fetched_utc": "2026-06-05T19:32:07Z"
    },
    "AERO": {
      "price": 0.31085860057109865,
      "fdv_usd": 594492761.4,
      "mcap_usd": 294656325.63,
      "circulating_supply": 947878955.529626,
      "total_supply": 1912421790.1970837,
      "max_supply": null,
      "date_launched": null,
      "slug": "aerodrome-finance",
      "fetched_utc": "2026-06-05T19:32:08Z"
    },
    "ALLO": {
      "price": 0.21468949013698677,
      "fdv_usd": 214689490.14,
      "mcap_usd": 43045242.77,
      "circulating_supply": 200500000.0,
      "total_supply": 785499999.0,
      "max_supply": 1000000000.0,
      "date_launched": "2025-11-10T00:00:00.000Z",
      "slug": "allora",
      "fetched_utc": "2026-06-05T19:32:10Z"
    },
    "ASTER": {
      "price": 0.5992988358659809,
      "fdv_usd": 4794390686.93,
      "mcap_usd": 1558441302.38,
      "circulating_supply": 2600441063.984935,
      "total_supply": 7822218820.515041,
      "max_supply": 8000000000.0,
      "date_launched": "2025-09-17T00:00:00.000Z",
      "slug": "aster",
      "fetched_utc": "2026-06-05T19:32:12Z"
    },
    "ATH": {
      "price": 0.004161565058723291,
      "fdv_usd": 174785732.47,
      "mcap_usd": 83767163.41,
      "circulating_supply": 20128764593.0,
      "total_supply": 42000000000.0,
      "max_supply": 42000000000.0,
      "date_launched": "2024-03-20T00:00:00.000Z",
      "slug": "aethir",
      "fetched_utc": "2026-06-05T19:32:13Z"
    },
    "AVNT": {
      "price": 0.10196256577105561,
      "fdv_usd": 101962565.77,
      "mcap_usd": 33031093.38,
      "circulating_supply": 323953140.3164983,
      "total_supply": 1000000000.0,
      "max_supply": 1000000000.0,
      "date_launched": "2023-06-18T00:00:00.000Z",
      "slug": "avantis",
      "fetched_utc": "2026-06-05T19:32:15Z"
    },
    "B3": {
      "price": 0.0006003931362607351,
      "fdv_usd": 60039313.63,
      "mcap_usd": 27877203.94,
      "circulating_supply": 46431583333.0,
      "total_supply": 100000000000.0,
      "max_supply": 100000000000.0,
      "date_launched": "2025-02-09T00:00:00.000Z",
      "slug": "b3",
      "fetched_utc": "2026-06-05T19:32:16Z"
    },
    "BARD": {
      "price": 0.15251374726046782,
      "fdv_usd": 152513747.26,
      "mcap_usd": 49185683.49,
      "circulating_supply": 322500000.0,
      "total_supply": 1000000000.0,
      "max_supply": 1000000000.0,
      "date_launched": "2025-09-18T00:00:00.000Z",
      "slug": "lombard",
      "fetched_utc": "2026-06-05T19:32:18Z"
    },
    "BIGTIME": {
      "price": 0.008423466837409042,
      "fdv_usd": 42117334.19,
      "mcap_usd": 20495046.91,
      "circulating_supply": 2433089286.1052065,
      "total_supply": 5000000000.0,
      "max_supply": 5000000000.0,
      "date_launched": "2023-10-10T00:00:00.000Z",
      "slug": "big-time",
      "fetched_utc": "2026-06-05T19:32:20Z"
    },
    "BILL": {
      "price": 0.06770786696180126,
      "fdv_usd": 677078669.62,
      "mcap_usd": 164407866.37,
      "circulating_supply": 2428194444.0,
      "total_supply": 10000000000.0,
      "max_supply": 10000000000.0,
      "date_launched": "2026-05-04T00:00:00.000Z",
      "slug": "billions-network",
      "fetched_utc": "2026-06-05T19:32:21Z"
    },
    "BIRB": {
      "price": 0.07541513336544993,
      "fdv_usd": 75415133.37,
      "mcap_usd": 21493313.01,
      "circulating_supply": 285000000.0,
      "total_supply": 1000000000.0,
      "max_supply": 1000000000.0,
      "date_launched": "2026-01-28T00:00:00.000Z",
      "slug": "moonbirds",
      "fetched_utc": "2026-06-05T19:32:23Z"
    },
    "BREV": {
      "price": 0.07943401410109746,
      "fdv_usd": 79434014.1,
      "mcap_usd": 19858503.53,
      "circulating_supply": 250000000.0,
      "total_supply": 1000000000.0,
      "max_supply": 1000000000.0,
      "date_launched": "2026-01-06T00:00:00.000Z",
      "slug": "brevis",
      "fetched_utc": "2026-06-05T19:32:25Z"
    },
    "CFG": {
      "price": 0.19186751746250477,
      "fdv_usd": 130469911.87,
      "mcap_usd": 110737515.96,
      "circulating_supply": 577156141.0,
      "total_supply": 680000000.0,
      "max_supply": null,
      "date_launched": "2025-05-20T00:00:00.000Z",
      "slug": "centrifuge",
      "fetched_utc": "2026-06-05T19:32:26Z"
    },
    "CHIP": {
      "price": 0.031161142087003383,
      "fdv_usd": 311611420.87,
      "mcap_usd": 62322284.17,
      "circulating_supply": 2000000000.0,
      "total_supply": 10000000000.0,
      "max_supply": 10000000000.0,
      "date_launched": null,
      "slug": "usd-ai",
      "fetched_utc": "2026-06-05T19:32:28Z"
    },
    "CTR": {
      "price": 0.013609454369555256,
      "fdv_usd": 136094543.7,
      "mcap_usd": 16331345.24,
      "circulating_supply": 1200000000.0,
      "total_supply": 10000000000.0,
      "max_supply": 10000000000.0,
      "date_launched": "2026-05-26T00:00:00.000Z",
      "slug": "citrea",
      "fetched_utc": "2026-06-05T19:32:29Z"
    },
    "DOOD": {
      "price": 0.001584359906524885,
      "fdv_usd": 15843599.07,
      "mcap_usd": 12358007.27,
      "circulating_supply": 7800000000.0,
      "total_supply": 10000000000.0,
      "max_supply": 10000000000.0,
      "date_launched": null,
      "slug": "doodles",
      "fetched_utc": "2026-06-05T19:32:31Z"
    },
    "DRIFT": {
      "price": 0.016238153748308108,
      "fdv_usd": 16238153.75,
      "mcap_usd": 9929887.97,
      "circulating_supply": 611515824.085346,
      "total_supply": 1000000000.0,
      "max_supply": null,
      "date_launched": "2022-11-04T00:00:00.000Z",
      "slug": "drift",
      "fetched_utc": "2026-06-05T19:32:32Z"
    },
    "EDGE": {
      "price": 0.49217335163496895,
      "fdv_usd": 492173351.63,
      "mcap_usd": 172260673.07,
      "circulating_supply": 350000000.0,
      "total_supply": 1000000000.0,
      "max_supply": 1000000000.0,
      "date_launched": "2024-08-02T00:00:00.000Z",
      "slug": "edgex",
      "fetched_utc": "2026-06-05T19:32:34Z"
    },
    "ELSA": {
      "price": 0.04395734879884392,
      "fdv_usd": 43957348.8,
      "mcap_usd": 11237549.14,
      "circulating_supply": 255646654.0,
      "total_supply": 1000000000.0,
      "max_supply": 1000000000.0,
      "date_launched": "2026-01-20T00:00:00.000Z",
      "slug": "heyelsa",
      "fetched_utc": "2026-06-05T19:32:36Z"
    },
    "ERA": {
      "price": 0.09735652018022836,
      "fdv_usd": 97356520.18,
      "mcap_usd": 14457443.25,
      "circulating_supply": 148500000.0,
      "total_supply": 1000000000.0,
      "max_supply": 1000000000.0,
      "date_launched": "2025-07-15T00:00:00.000Z",
      "slug": "caldera",
      "fetched_utc": "2026-06-05T19:32:37Z"
    },
    "ESP": {
      "price": 0.0637339980281228,
      "fdv_usd": 228805052.92,
      "mcap_usd": 33176732.67,
      "circulating_supply": 520550000.0,
      "total_supply": 3590000000.0,
      "max_supply": null,
      "date_launched": "2026-02-09T00:00:00.000Z",
      "slug": "espresso",
      "fetched_utc": "2026-06-05T19:32:39Z"
    },
    "EUL": {
      "price": 0.8550538537195802,
      "fdv_usd": 23242773.53,
      "mcap_usd": 20426813.09,
      "circulating_supply": 23889504.74287801,
      "total_supply": 27182818.28459045,
      "max_supply": 27182818.28459045,
      "date_launched": "2021-12-30T00:00:00.000Z",
      "slug": "euler-finance",
      "fetched_utc": "2026-06-05T19:32:40Z"
    },
    "FLOCK": {
      "price": 0.039537916132476945,
      "fdv_usd": 39537916.13,
      "mcap_usd": 15307406.47,
      "circulating_supply": 387157644.32500446,
      "total_supply": 388499032.8403433,
      "max_supply": 1000000000.0,
      "date_launched": "2024-12-31T00:00:00.000Z",
      "slug": "flock-io",
      "fetched_utc": "2026-06-05T19:32:42Z"
    },
    "FLUID": {
      "price": 1.0749245083611045,
      "fdv_usd": 107492450.84,
      "mcap_usd": 83787137.24,
      "circulating_supply": 77946996.82034639,
      "total_supply": 100000000.0,
      "max_supply": null,
      "date_launched": null,
      "slug": "instadapp",
      "fetched_utc": "2026-06-05T19:32:43Z"
    },
    "G": {
      "price": 5.122476160845045e-06,
      "fdv_usd": 450777.9,
      "mcap_usd": null,
      "circulating_supply": null,
      "total_supply": 87998054353.05655,
      "max_supply": 88000000000.0,
      "date_launched": "2022-02-21T00:00:00.000Z",
      "slug": "giants-protocol",
      "fetched_utc": "2026-06-05T19:32:45Z"
    },
    "GWEI": {
      "price": 0.09890963598348847,
      "fdv_usd": 989096359.83,
      "mcap_usd": 173091862.97,
      "circulating_supply": 1750000000.0,
      "total_supply": 10000000000.0,
      "max_supply": 10000000000.0,
      "date_launched": "2026-01-21T00:00:00.000Z",
      "slug": "eth-gas",
      "fetched_utc": "2026-06-05T19:32:47Z"
    },
    "HOME": {
      "price": 0.04528886500069948,
      "fdv_usd": 452888650.01,
      "mcap_usd": 173682797.28,
      "circulating_supply": 3835000000.01,
      "total_supply": 10000000000.0,
      "max_supply": 10000000000.0,
      "date_launched": "2025-06-09T00:00:00.000Z",
      "slug": "defi-app",
      "fetched_utc": "2026-06-05T19:32:48Z"
    },
    "HYPER": {
      "price": 0.0627516367125779,
      "fdv_usd": 62751636.71,
      "mcap_usd": 21220973.08,
      "circulating_supply": 338174017.3333334,
      "total_supply": 808000000.0,
      "max_supply": 1000000000.0,
      "date_launched": "2025-04-22T00:00:00.000Z",
      "slug": "hyperlane",
      "fetched_utc": "2026-06-05T19:32:50Z"
    },
    "IP": {
      "price": 0.3104094910370191,
      "fdv_usd": 319345015.01,
      "mcap_usd": 110275814.73,
      "circulating_supply": 355259159.0,
      "total_supply": 1028786246.0,
      "max_supply": null,
      "date_launched": "2025-02-12T00:00:00.000Z",
      "slug": "story-protocol",
      "fetched_utc": "2026-06-05T19:32:51Z"
    },
    "IRYS": {
      "price": 0.0180745547765403,
      "fdv_usd": 180745547.77,
      "mcap_usd": 46394005.1,
      "circulating_supply": 2566813162.0,
      "total_supply": 10000000000.0,
      "max_supply": null,
      "date_launched": "2025-11-25T00:00:00.000Z",
      "slug": "irys",
      "fetched_utc": "2026-06-05T19:32:53Z"
    },
    "KAT": {
      "price": 0.0050793536179783595,
      "fdv_usd": 50793536.18,
      "mcap_usd": 11895846.17,
      "circulating_supply": 2342000000.0,
      "total_supply": 10000000000.0,
      "max_supply": 10000000000.0,
      "date_launched": "2025-06-26T00:00:00.000Z",
      "slug": "katana-network",
      "fetched_utc": "2026-06-05T19:32:54Z"
    },
    "KITE": {
      "price": 0.17279149288723247,
      "fdv_usd": 1727914928.87,
      "mcap_usd": 311024687.2,
      "circulating_supply": 1800000000.0,
      "total_supply": 10000000000.0,
      "max_supply": 10000000000.0,
      "date_launched": "2025-11-02T00:00:00.000Z",
      "slug": "kite",
      "fetched_utc": "2026-06-05T19:32:56Z"
    },
    "KMNO": {
      "price": 0.014174266356585818,
      "fdv_usd": 141742663.57,
      "mcap_usd": 67628729.48,
      "circulating_supply": 4771233147.25,
      "total_supply": 9999957987.790766,
      "max_supply": 10000000000.0,
      "date_launched": "2024-04-30T00:00:00.000Z",
      "slug": "kamino-finance",
      "fetched_utc": "2026-06-05T19:32:57Z"
    },
    "LA": {
      "price": 0.07618191876667285,
      "fdv_usd": 76181918.77,
      "mcap_usd": 14703110.32,
      "circulating_supply": 193000000.0,
      "total_supply": 1000000000.0,
      "max_supply": null,
      "date_launched": "2025-05-31T00:00:00.000Z",
      "slug": "lagrange",
      "fetched_utc": "2026-06-05T19:32:59Z"
    },
    "LINEA": {
      "price": 0.002376309770702791,
      "fdv_usd": 171118042.83,
      "mcap_usd": 36790379.21,
      "circulating_supply": 15482147850.0,
      "total_supply": 72009990000.0,
      "max_supply": 72009990000.0,
      "date_launched": "2025-09-10T00:00:00.000Z",
      "slug": "linea",
      "fetched_utc": "2026-06-05T19:33:00Z"
    },
    "MET": {
      "price": 0.10133669525969191,
      "fdv_usd": 101336695.26,
      "mcap_usd": 53087534.75,
      "circulating_supply": 523872765.039079,
      "total_supply": 997734161.529733,
      "max_supply": 1000000000.0,
      "date_launched": "2025-10-23T00:00:00.000Z",
      "slug": "meteora",
      "fetched_utc": "2026-06-05T19:33:02Z"
    },
    "MOG": {
      "price": 1.0206325796568884e-07,
      "fdv_usd": 42936991.99,
      "mcap_usd": 39862594.2,
      "circulating_supply": 390567526433216.7,
      "total_supply": 390567526433216.7,
      "max_supply": 420690000000000.0,
      "date_launched": "2023-07-19T00:00:00.000Z",
      "slug": "mog-coin",
      "fetched_utc": "2026-06-05T19:33:04Z"
    },
    "MOODENG": {
      "price": 0.03605562082068892,
      "fdv_usd": 35694047.53,
      "mcap_usd": 35694047.53,
      "circulating_supply": 989971791.17,
      "total_supply": 989971791.17,
      "max_supply": 989971791.17,
      "date_launched": null,
      "slug": "moo-deng-solana",
      "fetched_utc": "2026-06-05T19:33:05Z"
    },
    "MORPHO": {
      "price": 1.6204196663394126,
      "fdv_usd": 1620419666.34,
      "mcap_usd": 813574805.86,
      "circulating_supply": 502076605.6849661,
      "total_supply": 999999999.8010328,
      "max_supply": 1000000000.0,
      "date_launched": "2024-11-21T00:00:00.000Z",
      "slug": "morpho",
      "fetched_utc": "2026-06-05T19:33:07Z"
    },
    "NEWT": {
      "price": 0.054179322044661214,
      "fdv_usd": 54179322.04,
      "mcap_usd": 13084609.82,
      "circulating_supply": 241505602.62265345,
      "total_supply": 1000000000.0,
      "max_supply": 1000000000.0,
      "date_launched": "2025-06-22T00:00:00.000Z",
      "slug": "newton-protocol",
      "fetched_utc": "2026-06-05T19:33:08Z"
    },
    "NEX": {
      "price": 3.032838150445649e-06,
      "fdv_usd": 303283815.04,
      "mcap_usd": 181970289.03,
      "circulating_supply": 60000000000000.0,
      "total_supply": 100000000000000.0,
      "max_supply": 100000000000000.0,
      "date_launched": "2026-05-20T00:00:00.000Z",
      "slug": "nexus-labs",
      "fetched_utc": "2026-06-05T19:33:10Z"
    },
    "ONDO": {
      "price": 0.3270777934966522,
      "fdv_usd": 3270777934.97,
      "mcap_usd": 1592649923.83,
      "circulating_supply": 4869330647.0,
      "total_supply": 10000000000.0,
      "max_supply": null,
      "date_launched": "2021-03-09T00:00:00.000Z",
      "slug": "ondo-finance",
      "fetched_utc": "2026-06-05T19:33:12Z"
    },
    "OPG": {
      "price": 0.1635820239651107,
      "fdv_usd": 163582023.97,
      "mcap_usd": 31080584.55,
      "circulating_supply": 190000000.0,
      "total_supply": 1000000000.0,
      "max_supply": 1000000000.0,
      "date_launched": "2026-04-21T00:00:00.000Z",
      "slug": "opengradient",
      "fetched_utc": "2026-06-05T19:33:13Z"
    },
    "PEPE": {
      "price": 2.648973961525884e-06,
      "fdv_usd": 1096072536.72,
      "mcap_usd": 1096072536.72,
      "circulating_supply": 413772484228231.0,
      "total_supply": 413772484228231.0,
      "max_supply": 413772484228231.0,
      "date_launched": "2023-04-14T00:00:00.000Z",
      "slug": "pepe",
      "fetched_utc": "2026-06-05T19:33:15Z"
    },
    "PLUME": {
      "price": 0.010956904052895294,
      "fdv_usd": 109569040.53,
      "mcap_usd": 63086322.23,
      "circulating_supply": 5757677709.0,
      "total_supply": 10000000000.0,
      "max_supply": 10000000000.0,
      "date_launched": "2025-01-20T00:00:00.000Z",
      "slug": "plume",
      "fetched_utc": "2026-06-05T19:33:16Z"
    },
    "POPCAT": {
      "price": 0.04046688537144125,
      "fdv_usd": 39656464.0,
      "mcap_usd": 39654990.4,
      "circulating_supply": 979936805.9773552,
      "total_supply": 979936805.9773552,
      "max_supply": 979973220.96,
      "date_launched": "2023-12-12T00:00:00.000Z",
      "slug": "popcat-sol",
      "fetched_utc": "2026-06-05T19:33:18Z"
    },
    "PRL": {
      "price": 0.17388647113826547,
      "fdv_usd": 173886471.14,
      "mcap_usd": 30430132.45,
      "circulating_supply": 175000000.0,
      "total_supply": 1000000000.0,
      "max_supply": 1000000000.0,
      "date_launched": "2026-03-25T00:00:00.000Z",
      "slug": "perle",
      "fetched_utc": "2026-06-05T19:33:19Z"
    },
    "PROMPT": {
      "price": 0.02400983832383593,
      "fdv_usd": 24009838.32,
      "mcap_usd": 11101528.47,
      "circulating_supply": 462374145.0,
      "total_supply": 1000000000.0,
      "max_supply": 1000000000.0,
      "date_launched": "2025-04-10T00:00:00.000Z",
      "slug": "wayfinder",
      "fetched_utc": "2026-06-05T19:33:21Z"
    },
    "PROVE": {
      "price": 0.18258224576566337,
      "fdv_usd": 182582245.77,
      "mcap_usd": 35603537.92,
      "circulating_supply": 195000000.0,
      "total_supply": 1000000000.0,
      "max_supply": 1000000000.0,
      "date_launched": "2025-01-20T00:00:00.000Z",
      "slug": "succinct",
      "fetched_utc": "2026-06-05T19:33:23Z"
    },
    "PUMP": {
      "price": 0.0013745374930897968,
      "fdv_usd": 1374537493.09,
      "mcap_usd": 481666550.84,
      "circulating_supply": 350420816649.04596,
      "total_supply": 860882620320.2686,
      "max_supply": 1000000000000.0,
      "date_launched": "2025-07-14T00:00:00.000Z",
      "slug": "pump-fun",
      "fetched_utc": "2026-06-05T19:33:24Z"
    },
    "QAIT": {
      "price": 0.02681264580023432,
      "fdv_usd": 268126458.0,
      "mcap_usd": 13406322.9,
      "circulating_supply": 500000000.0,
      "total_supply": 10000000000.0,
      "max_supply": 10000000000.0,
      "date_launched": "2026-05-27T00:00:00.000Z",
      "slug": "qait",
      "fetched_utc": "2026-06-05T19:33:26Z"
    },
    "RECALL": {
      "price": 0.03716415185662082,
      "fdv_usd": 37164151.86,
      "mcap_usd": 9116022.09,
      "circulating_supply": 245290734.14714,
      "total_supply": 1000000000.0,
      "max_supply": 1000000000.0,
      "date_launched": "2025-10-15T00:00:00.000Z",
      "slug": "recall-network",
      "fetched_utc": "2026-06-05T19:33:27Z"
    },
    "ROBO": {
      "price": 0.019120464520828686,
      "fdv_usd": 191204645.21,
      "mcap_usd": 42657756.35,
      "circulating_supply": 2231000000.0,
      "total_supply": 10000000000.0,
      "max_supply": 10000000000.0,
      "date_launched": "2025-01-27T00:00:00.000Z",
      "slug": "fabric-foundation",
      "fetched_utc": "2026-06-05T19:33:29Z"
    },
    "SAFE": {
      "price": 0.0946116393267378,
      "fdv_usd": 94611639.33,
      "mcap_usd": 70941961.1,
      "circulating_supply": 749822766.0,
      "total_supply": 1000000000.0,
      "max_supply": 1000000000.0,
      "date_launched": null,
      "slug": "safe1",
      "fetched_utc": "2026-06-05T19:33:30Z"
    },
    "SAPIEN": {
      "price": 0.07300613966467148,
      "fdv_usd": 73006139.66,
      "mcap_usd": 18251534.92,
      "circulating_supply": 250000000.0,
      "total_supply": 1000000000.0,
      "max_supply": 1000000000.0,
      "date_launched": "2025-08-20T00:00:00.000Z",
      "slug": "sapien-io",
      "fetched_utc": "2026-06-05T19:33:32Z"
    },
    "SENT": {
      "price": 0.012082993632509037,
      "fdv_usd": 415168499.92,
      "mcap_usd": 87455244.5,
      "circulating_supply": 7237878887.0,
      "total_supply": 34359738368.0,
      "max_supply": null,
      "date_launched": "2025-11-09T00:00:00.000Z",
      "slug": "sentient",
      "fetched_utc": "2026-06-05T19:33:34Z"
    },
    "SIGN": {
      "price": 0.008691844823768457,
      "fdv_usd": 86918448.24,
      "mcap_usd": 20020215.91,
      "circulating_supply": 2303333333.0,
      "total_supply": 10000000000.0,
      "max_supply": 10000000000.0,
      "date_launched": "2025-04-28T00:00:00.000Z",
      "slug": "sign",
      "fetched_utc": "2026-06-05T19:33:35Z"
    },
    "SKR": {
      "price": 0.009830061035077555,
      "fdv_usd": 101729753.23,
      "mcap_usd": 49167706.72,
      "circulating_supply": 5001770237.781052,
      "total_supply": 10348842480.923468,
      "max_supply": null,
      "date_launched": "2026-01-21T00:00:00.000Z",
      "slug": "solana-mobile-seeker",
      "fetched_utc": "2026-06-05T19:33:37Z"
    },
    "SLX": {
      "price": 0.17574038053052216,
      "fdv_usd": 175740380.53,
      "mcap_usd": 42679293.56,
      "circulating_supply": 242854223.0,
      "total_supply": 1000000000.0,
      "max_supply": 1000000000.0,
      "date_launched": "2025-09-29T00:00:00.000Z",
      "slug": "solstice",
      "fetched_utc": "2026-06-05T19:33:38Z"
    },
    "SPK": {
      "price": 0.018263442675028302,
      "fdv_usd": 182634426.75,
      "mcap_usd": 50329476.5,
      "circulating_supply": 2755749690.56972,
      "total_supply": 10000000000.0,
      "max_supply": 10000000000.0,
      "date_launched": "2025-06-17T00:00:00.000Z",
      "slug": "spark",
      "fetched_utc": "2026-06-05T19:33:40Z"
    },
    "SPX": {
      "price": 0.2726100534197071,
      "fdv_usd": 272610053.42,
      "mcap_usd": 253798076.02,
      "circulating_supply": 930993090.07,
      "total_supply": 930993090.07,
      "max_supply": 1000000000.0,
      "date_launched": null,
      "slug": "spx6900",
      "fetched_utc": "2026-06-05T19:33:41Z"
    },
    "SXT": {
      "price": 0.008386111562040955,
      "fdv_usd": 41930557.81,
      "mcap_usd": 11740556.19,
      "circulating_supply": 1400000000.0,
      "total_supply": 5000000000.0,
      "max_supply": 5000000000.0,
      "date_launched": "2025-05-05T00:00:00.000Z",
      "slug": "space-and-time",
      "fetched_utc": "2026-06-05T19:33:43Z"
    },
    "TOSHI": {
      "price": 0.00011536625646224964,
      "fdv_usd": 48533430.43,
      "mcap_usd": 48531051.91,
      "circulating_supply": 420669382891.91895,
      "total_supply": 420690000000.0,
      "max_supply": 420690000000.0,
      "date_launched": "2023-07-30T00:00:00.000Z",
      "slug": "toshithecat",
      "fetched_utc": "2026-06-05T19:33:44Z"
    },
    "TOWNS": {
      "price": 0.0021384336521978855,
      "fdv_usd": 22519030.18,
      "mcap_usd": 6520250.46,
      "circulating_supply": 3049077748.0,
      "total_supply": 10530619062.0,
      "max_supply": null,
      "date_launched": "2025-08-01T00:00:00.000Z",
      "slug": "towns",
      "fetched_utc": "2026-06-05T19:33:46Z"
    },
    "TREE": {
      "price": 0.043828672821754774,
      "fdv_usd": 43828672.82,
      "mcap_usd": 6842639.74,
      "circulating_supply": 156122449.0,
      "total_supply": 1000000000.0,
      "max_supply": 1000000000.0,
      "date_launched": "2021-06-29T00:00:00.000Z",
      "slug": "treehouse",
      "fetched_utc": "2026-06-05T19:33:48Z"
    },
    "TRUST": {
      "price": 0.04898302505454698,
      "fdv_usd": 51243780.06,
      "mcap_usd": 8799694.26,
      "circulating_supply": 179647832.0,
      "total_supply": 1046153846.1538461,
      "max_supply": null,
      "date_launched": "2025-11-05T00:00:00.000Z",
      "slug": "intuition",
      "fetched_utc": "2026-06-05T19:33:49Z"
    },
    "VIRTUAL": {
      "price": 0.5372019403504147,
      "fdv_usd": 537201940.35,
      "mcap_usd": 352945741.9,
      "circulating_supply": 657007570.8827373,
      "total_supply": 1000000000.0,
      "max_supply": 1000000000.0,
      "date_launched": "2023-12-23T00:00:00.000Z",
      "slug": "virtual-protocol",
      "fetched_utc": "2026-06-05T19:33:51Z"
    },
    "VVV": {
      "price": 15.133128930516463,
      "fdv_usd": 1214117673.86,
      "mcap_usd": 707900955.27,
      "circulating_supply": 46778227.98702135,
      "total_supply": 80229123.7613428,
      "max_supply": null,
      "date_launched": "2025-01-26T00:00:00.000Z",
      "slug": "venice-token",
      "fetched_utc": "2026-06-05T19:33:52Z"
    },
    "WAL": {
      "price": 0.034637063055024855,
      "fdv_usd": 173185315.28,
      "mcap_usd": 83237192.15,
      "circulating_supply": 2403125000.0,
      "total_supply": 5000000000.0,
      "max_supply": 5000000000.0,
      "date_launched": "2025-03-23T00:00:00.000Z",
      "slug": "walrus-xyz",
      "fetched_utc": "2026-06-05T19:33:54Z"
    },
    "WET": {
      "price": 0.05398722441438421,
      "fdv_usd": 53987224.41,
      "mcap_usd": 12417061.62,
      "circulating_supply": 230000000.0,
      "total_supply": 1000000000.0,
      "max_supply": 1000000000.0,
      "date_launched": null,
      "slug": "humidifi",
      "fetched_utc": "2026-06-05T19:33:55Z"
    },
    "XAN": {
      "price": 0.007666472931286965,
      "fdv_usd": 76664729.31,
      "mcap_usd": 19166182.33,
      "circulating_supply": 2500000000.0,
      "total_supply": 10000000000.0,
      "max_supply": 10000000000.0,
      "date_launched": "2025-09-30T00:00:00.000Z",
      "slug": "anoma",
      "fetched_utc": "2026-06-05T19:33:57Z"
    },
    "XPL": {
      "price": 0.0631426952203033,
      "fdv_usd": 631426952.2,
      "mcap_usd": 113656851.4,
      "circulating_supply": 1800000000.0,
      "total_supply": 10000000000.0,
      "max_supply": null,
      "date_launched": "2025-09-25T00:00:00.000Z",
      "slug": "plasma-xpl",
      "fetched_utc": "2026-06-05T19:33:59Z"
    },
    "YB": {
      "price": 0.07804896591516368,
      "fdv_usd": 78048965.92,
      "mcap_usd": 9378991.15,
      "circulating_supply": 120168038.60946342,
      "total_supply": 736815617.9314514,
      "max_supply": 1000000000.0,
      "date_launched": "2025-09-14T00:00:00.000Z",
      "slug": "yieldbasis",
      "fetched_utc": "2026-06-05T19:34:01Z"
    },
    "ZAMA": {
      "price": 0.029034130123679294,
      "fdv_usd": 319375431.36,
      "mcap_usd": 63875086.27,
      "circulating_supply": 2200000000.0,
      "total_supply": 11000000000.0,
      "max_supply": null,
      "date_launched": "2026-02-01T00:00:00.000Z",
      "slug": "zama",
      "fetched_utc": "2026-06-05T19:34:02Z"
    },
    "ZEST": {
      "price": 0.22845609920928614,
      "fdv_usd": 228456099.21,
      "mcap_usd": 33354590.48,
      "circulating_supply": 146000000.0,
      "total_supply": 1000000000.0,
      "max_supply": 1000000000.0,
      "date_launched": "2026-05-19T00:00:00.000Z",
      "slug": "zest-protocol",
      "fetched_utc": "2026-06-05T19:34:04Z"
    },
    "ZETA": {
      "price": 0.035981489267104115,
      "fdv_usd": 75561127.46,
      "mcap_usd": 52575327.53,
      "circulating_supply": 1461177083.0,
      "total_supply": 2100000000.0,
      "max_supply": 2100000000.0,
      "date_launched": "2021-06-25T00:00:00.000Z",
      "slug": "zetachain",
      "fetched_utc": "2026-06-05T19:34:06Z"
    },
    "ZKC": {
      "price": 0.04768216420187472,
      "fdv_usd": 50098961.06,
      "mcap_usd": 14337681.03,
      "circulating_supply": 300692749.0,
      "total_supply": 1050685553.0,
      "max_supply": null,
      "date_launched": "2025-09-14T00:00:00.000Z",
      "slug": "boundless",
      "fetched_utc": "2026-06-05T19:34:07Z"
    },
    "ZKP": {
      "price": 0.05157066665102012,
      "fdv_usd": 51570666.65,
      "mcap_usd": 14181933.33,
      "circulating_supply": 275000000.0,
      "total_supply": 1000000000.0,
      "max_supply": 1000000000.0,
      "date_launched": "2025-12-19T00:00:00.000Z",
      "slug": "zkpass",
      "fetched_utc": "2026-06-05T19:34:09Z"
    },
    "ZORA": {
      "price": 0.008784615889419978,
      "fdv_usd": 87846158.89,
      "mcap_usd": 39267233.02,
      "circulating_supply": 4469999999.0,
      "total_supply": 10000000000.0,
      "max_supply": 10000000000.0,
      "date_launched": "2025-04-23T00:00:00.000Z",
      "slug": "zora",
      "fetched_utc": "2026-06-05T19:34:11Z"
    }
  }
}