{"symbol": "AERO", "total_oi_usd": 18134014.44, "n_venues": 5, "venues": [{"oi_usd": 7723095.01, "oi_coins": 21453041.694444444, "mark": 0.36, "funding": 5e-05, "interval_h": 4.0, "vol24h_usd": 6543395.598377644, "funding_annualized": 0.1095, "venue": "Binance", "oi_share_pct": 42.58899779501885, "oi_vol_ratio": 1.1802885663698597}, {"oi_usd": 6738370.28, "oi_coins": 18717695.222222224, "mark": 0.36, "funding": -7.722e-05, "interval_h": 4.0, "vol24h_usd": 4069502.81395017, "funding_annualized": -0.16911179999999998, "venue": "Bybit", "oi_share_pct": 37.158734500268764, "oi_vol_ratio": 1.6558215064751913}, {"oi_usd": 1895221.85, "oi_coins": 5264505.138888889, "mark": 0.36, "funding": 5e-05, "interval_h": 4.0, "vol24h_usd": 579756.9815246649, "funding_annualized": 0.1095, "venue": "Bitget", "oi_share_pct": 10.45119852678357, "oi_vol_ratio": 3.268993579026647}, {"oi_usd": 1031737.85, "oi_coins": 2865938.4722222225, "mark": 0.36, "funding": -6.40661649535e-05, "interval_h": 4.0, "vol24h_usd": 1483411.409529103, "funding_annualized": -0.140304901248165, "venue": "OKX", "oi_share_pct": 5.6895170863225575, "oi_vol_ratio": 0.695516997760936}, {"oi_usd": 745589.45, "oi_coins": 2071081.8055555555, "mark": 0.36, "funding": 4.6e-05, "interval_h": 4.0, "vol24h_usd": 179141.8024978266, "funding_annualized": 0.10074, "venue": "Gate", "oi_share_pct": 4.111552091606253, "oi_vol_ratio": 4.162007078214174}], "others_oi_usd": 32515556.68, "n_others": 24, "fetched_at": 1781262176, "source": "coingecko"}