{"symbol": "AERO", "total_oi_usd": 15871298.75, "n_venues": 5, "venues": [{"oi_usd": 6847287.38, "oi_coins": 21397773.0625, "mark": 0.32, "funding": -9.671000000000001e-05, "interval_h": 4.0, "vol24h_usd": 12590912.753063202, "funding_annualized": -0.21179490000000004, "venue": "Binance", "oi_share_pct": 43.14257760411699, "oi_vol_ratio": 0.5438277203798546}, {"oi_usd": 5823427.3, "oi_coins": 18198210.3125, "mark": 0.32, "funding": -2.895e-05, "interval_h": 4.0, "vol24h_usd": 7177816.009043088, "funding_annualized": -0.0634005, "venue": "Bybit", "oi_share_pct": 36.69156123723019, "oi_vol_ratio": 0.8113090796230024}, {"oi_usd": 1587961.1, "oi_coins": 4962378.4375, "mark": 0.32, "funding": 5e-05, "interval_h": 4.0, "vol24h_usd": 739220.1237765815, "funding_annualized": 0.1095, "venue": "Bitget", "oi_share_pct": 10.005237284062844, "oi_vol_ratio": 2.148157292968851}, {"oi_usd": 1040912.44, "oi_coins": 3252851.3749999995, "mark": 0.32, "funding": 3.67482115685e-05, "interval_h": 4.0, "vol24h_usd": 2311994.5567980227, "funding_annualized": 0.080478583335015, "venue": "OKX", "oi_share_pct": 6.558457857772981, "oi_vol_ratio": 0.45022270356968436}, {"oi_usd": 571710.53, "oi_coins": 1786595.40625, "mark": 0.32, "funding": 3.4e-05, "interval_h": 4.0, "vol24h_usd": 554305.5989143082, "funding_annualized": 0.07446, "venue": "Gate", "oi_share_pct": 3.602166016816992, "oi_vol_ratio": 1.0313995224291113}], "others_oi_usd": 32908666.18, "n_others": 25, "fetched_at": 1780716358, "source": "coingecko"}