{"symbol": "BSB", "total_oi_usd": 27558259.27, "n_venues": 5, "venues": [{"oi_usd": 8806551.33, "oi_coins": 46350270.15789474, "mark": 0.19, "funding": 5e-05, "interval_h": 4.0, "vol24h_usd": 24925365.38998783, "funding_annualized": 0.1095, "venue": "Binance", "oi_share_pct": 31.9561233665685, "oi_vol_ratio": 0.35331683978191425}, {"oi_usd": 7932780.0, "oi_coins": 41751473.684210524, "mark": 0.19, "funding": 5e-05, "interval_h": 4.0, "vol24h_usd": 5623142.320164766, "funding_annualized": 0.1095, "venue": "Bitget", "oi_share_pct": 28.78549012214152, "oi_vol_ratio": 1.4107379021072968}, {"oi_usd": 5954518.46, "oi_coins": 31339570.842105262, "mark": 0.19, "funding": 5e-05, "interval_h": 4.0, "vol24h_usd": 6812713.22780303, "funding_annualized": 0.1095, "venue": "Bybit", "oi_share_pct": 21.60701952057656, "oi_vol_ratio": 0.8740303988870846}, {"oi_usd": 3821923.88, "oi_coins": 20115388.842105262, "mark": 0.19, "funding": 0.0001062549828717, "interval_h": 4.0, "vol24h_usd": 28704787.152392037, "funding_annualized": 0.232698412489023, "venue": "OKX", "oi_share_pct": 13.868524287238118, "oi_vol_ratio": 0.13314587074656326}, {"oi_usd": 1042485.6, "oi_coins": 5486766.315789473, "mark": 0.19, "funding": 5e-05, "interval_h": 4.0, "vol24h_usd": 3080699.3821897395, "funding_annualized": 0.1095, "venue": "Gate", "oi_share_pct": 3.7828427034752985, "oi_vol_ratio": 0.3383925111378471}], "others_oi_usd": 19163718.23, "n_others": 20, "fetched_at": 1780750084, "source": "coingecko"}