{"symbol": "BSB", "total_oi_usd": 38767517.7, "n_venues": 5, "venues": [{"oi_usd": 12127248.8, "oi_coins": 46643264.615384616, "mark": 0.26, "funding": 5e-05, "interval_h": 4.0, "vol24h_usd": 21149937.298455253, "funding_annualized": 0.1095, "venue": "Bitget", "oi_share_pct": 31.281984298932812, "oi_vol_ratio": 0.5733940781415815}, {"oi_usd": 11860665.11, "oi_coins": 45617942.730769224, "mark": 0.26, "funding": 5e-05, "interval_h": 4.0, "vol24h_usd": 72722320.5165382, "funding_annualized": 0.1095, "venue": "Binance", "oi_share_pct": 30.59433725363334, "oi_vol_ratio": 0.16309525089071789}, {"oi_usd": 7757380.29, "oi_coins": 29836078.038461536, "mark": 0.26, "funding": 5e-05, "interval_h": 4.0, "vol24h_usd": 28431885.782398034, "funding_annualized": 0.1095, "venue": "Bybit", "oi_share_pct": 20.00999999543432, "oi_vol_ratio": 0.27284086428071314}, {"oi_usd": 5737819.23, "oi_coins": 22068535.5, "mark": 0.26, "funding": 5e-05, "interval_h": 4.0, "vol24h_usd": 93560240.34497057, "funding_annualized": 0.1095, "venue": "OKX", "oi_share_pct": 14.800584536780903, "oi_vol_ratio": 0.06132753837360619}, {"oi_usd": 1284404.27, "oi_coins": 4940016.423076923, "mark": 0.26, "funding": 5e-05, "interval_h": 4.0, "vol24h_usd": 3227508.785323275, "funding_annualized": 0.1095, "venue": "Gate", "oi_share_pct": 3.313093915218616, "oi_vol_ratio": 0.397955313349008}], "others_oi_usd": 38020551.93, "n_others": 20, "fetched_at": 1781087885, "source": "coingecko"}