{"symbol": "BTW", "total_oi_usd": 5867609.01, "n_venues": 3, "venues": [{"oi_usd": 3212338.41, "oi_coins": 32123384.1, "mark": 0.1, "funding": 0.000287, "interval_h": 4.0, "vol24h_usd": 2690078.8640933577, "funding_annualized": 0.6285299999999999, "venue": "Bitget", "oi_share_pct": 54.74697452617075, "oi_vol_ratio": 1.1941428382928323}, {"oi_usd": 1938670.28, "oi_coins": 19386702.8, "mark": 0.1, "funding": 0.00014942000000000002, "interval_h": 4.0, "vol24h_usd": 7167343.461118345, "funding_annualized": 0.3272298, "venue": "Bybit", "oi_share_pct": 33.04020899647504, "oi_vol_ratio": 0.2704865883038766}, {"oi_usd": 716600.32, "oi_coins": 7166003.199999999, "mark": 0.1, "funding": 5e-05, "interval_h": 4.0, "vol24h_usd": 3499785.2946656677, "funding_annualized": 0.1095, "venue": "Gate", "oi_share_pct": 12.212816477354206, "oi_vol_ratio": 0.20475550917144372}], "others_oi_usd": 29904496.48, "n_others": 14, "fetched_at": 1781409672, "source": "coingecko"}