{"symbol": "GUA", "total_oi_usd": 5178166.78, "n_venues": 2, "venues": [{"oi_usd": 4495124.29, "oi_coins": 7491873.816666667, "mark": 0.6, "funding": -0.00055416, "interval_h": 4.0, "vol24h_usd": 7237808.201309823, "funding_annualized": -1.2136104, "venue": "Binance", "oi_share_pct": 86.80918326852346, "oi_vol_ratio": 0.6210615375503483}, {"oi_usd": 683042.49, "oi_coins": 1157699.1355932204, "mark": 0.59, "funding": 0.0005379999999999998, "interval_h": 4.0, "vol24h_usd": 238645.57427000706, "funding_annualized": 1.1782199999999996, "venue": "Gate", "oi_share_pct": 13.19081673147654, "oi_vol_ratio": 2.8621628206991003}], "others_oi_usd": 27679889.630000003, "n_others": 13, "fetched_at": 1781310123, "source": "coingecko"}