{"symbol": "GUA", "total_oi_usd": 11973632.05, "n_venues": 2, "venues": [{"oi_usd": 11096839.99, "oi_coins": 12329822.211111112, "mark": 0.9, "funding": 5e-05, "interval_h": 4.0, "vol24h_usd": 46363625.83109307, "funding_annualized": 0.1095, "venue": "Binance", "oi_share_pct": 92.67730913778998, "oi_vol_ratio": 0.2393436619997496}, {"oi_usd": 876792.06, "oi_coins": 974213.4, "mark": 0.9, "funding": 5e-05, "interval_h": 4.0, "vol24h_usd": 1890582.8890299858, "funding_annualized": 0.1095, "venue": "Gate", "oi_share_pct": 7.322690862210017, "oi_vol_ratio": 0.46376811357361947}], "others_oi_usd": 36496774.019999996, "n_others": 14, "fetched_at": 1780607910, "source": "coingecko"}