{"symbol": "H", "total_oi_usd": 263125981.36999997, "n_venues": 5, "venues": [{"oi_usd": 138873741.45, "oi_coins": 198391059.2142857, "mark": 0.7, "funding": 5e-05, "interval_h": 4.0, "vol24h_usd": 103783793.01105598, "funding_annualized": 0.1095, "venue": "Binance", "oi_share_pct": 52.778422232170165, "oi_vol_ratio": 1.3381062439605182}, {"oi_usd": 71011259.63, "oi_coins": 104428322.9852941, "mark": 0.68, "funding": 5e-05, "interval_h": 4.0, "vol24h_usd": 30421654.47056755, "funding_annualized": 0.1095, "venue": "Bybit", "oi_share_pct": 26.987551461193814, "oi_vol_ratio": 2.3342339812156574}, {"oi_usd": 25159126.03, "oi_coins": 36998714.75, "mark": 0.68, "funding": 5e-05, "interval_h": 4.0, "vol24h_usd": 14625966.3835077, "funding_annualized": 0.1095, "venue": "Bitget", "oi_share_pct": 9.561627437551286, "oi_vol_ratio": 1.7201684572699096}, {"oi_usd": 19030077.32, "oi_coins": 26802925.8028169, "mark": 0.71, "funding": 0.00030517618205829996, "interval_h": 4.0, "vol24h_usd": 52901589.252615005, "funding_annualized": 0.6683358387076769, "venue": "OKX", "oi_share_pct": 7.23230644914554, "oi_vol_ratio": 0.35972600424399}, {"oi_usd": 9051776.94, "oi_coins": 12931109.914285714, "mark": 0.7, "funding": 0.0001, "interval_h": 4.0, "vol24h_usd": 13170634.012615053, "funding_annualized": 0.219, "venue": "Gate", "oi_share_pct": 3.4400924199391993, "oi_vol_ratio": 0.6872696433087471}], "others_oi_usd": 72892833.05, "n_others": 26, "fetched_at": 1780757757, "source": "coingecko"}