{"symbol": "HYPE", "total_oi_usd": 1030929589.43, "n_venues": 5, "venues": [{"oi_usd": 466128773.66, "oi_coins": 6641903.300940438, "mark": 70.18, "funding": 5e-05, "interval_h": 4.0, "vol24h_usd": 1912494301.9891982, "funding_annualized": 0.1095, "venue": "Binance", "oi_share_pct": 45.214414101521925, "oi_vol_ratio": 0.24372818950371583}, {"oi_usd": 274157848.58, "oi_coins": 3902047.37517791, "mark": 70.26, "funding": 0.0001, "interval_h": 4.0, "vol24h_usd": 687569112.2451224, "funding_annualized": 0.219, "venue": "Bybit", "oi_share_pct": 26.593266057246606, "oi_vol_ratio": 0.39873496888886}, {"oi_usd": 133548520.63, "oi_coins": 1901858.738678439, "mark": 70.22, "funding": 5e-05, "interval_h": 4.0, "vol24h_usd": 264945623.02887762, "funding_annualized": 0.1095, "venue": "Bitget", "oi_share_pct": 12.954184456364167, "oi_vol_ratio": 0.504060112800746}, {"oi_usd": 122382986.94, "oi_coins": 1745585.322207959, "mark": 70.11, "funding": 0.0001, "interval_h": 4.0, "vol24h_usd": 811731085.6230232, "funding_annualized": 0.219, "venue": "OKX", "oi_share_pct": 11.871129531519745, "oi_vol_ratio": 0.15076789482081754}, {"oi_usd": 34711459.62, "oi_coins": 493691.64585407474, "mark": 70.31, "funding": 5e-05, "interval_h": 4.0, "vol24h_usd": 108937398.30799387, "funding_annualized": 0.1095, "venue": "Gate", "oi_share_pct": 3.367005853347553, "oi_vol_ratio": 0.31863675981926637}], "fetched_at": 1780556397, "source": "coingecko"}