{"symbol": "KAS", "total_oi_usd": 16682311.02, "n_venues": 4, "venues": [{"oi_usd": 6924913.87, "oi_coins": 230830462.33333334, "mark": 0.03, "funding": 5e-05, "interval_h": 4.0, "vol24h_usd": 3255057.5609134133, "funding_annualized": 0.1095, "venue": "Bitget", "oi_share_pct": 41.5105189065106, "oi_vol_ratio": 2.1274320777469677}, {"oi_usd": 6763911.12, "oi_coins": 225463704.0, "mark": 0.03, "funding": 5e-05, "interval_h": 4.0, "vol24h_usd": 7309829.139986904, "funding_annualized": 0.1095, "venue": "Bybit", "oi_share_pct": 40.54540831837339, "oi_vol_ratio": 0.9253172667196046}, {"oi_usd": 2321187.91, "oi_coins": 77372930.33333334, "mark": 0.03, "funding": 1.155e-05, "interval_h": 4.0, "vol24h_usd": 12392970.386635518, "funding_annualized": 0.025294499999999998, "venue": "Binance", "oi_share_pct": 13.91406686529934, "oi_vol_ratio": 0.18729875385671468}, {"oi_usd": 672298.12, "oi_coins": 22409937.333333336, "mark": 0.03, "funding": 6.9e-05, "interval_h": 4.0, "vol24h_usd": 1762646.7841068248, "funding_annualized": 0.15111, "venue": "Gate", "oi_share_pct": 4.030005909816684, "oi_vol_ratio": 0.38141397701563307}], "others_oi_usd": 61372657.02, "n_others": 29, "fetched_at": 1780744200, "source": "coingecko"}