{"symbol": "KAS", "total_oi_usd": 17024914.04, "n_venues": 4, "venues": [{"oi_usd": 7170946.44, "oi_coins": 239031548.00000003, "mark": 0.03, "funding": 5e-05, "interval_h": 4.0, "vol24h_usd": 8014666.127075774, "funding_annualized": 0.1095, "venue": "Bybit", "oi_share_pct": 42.12030923123534, "oi_vol_ratio": 0.8947280306255736}, {"oi_usd": 6949821.85, "oi_coins": 231660728.33333334, "mark": 0.03, "funding": 5e-05, "interval_h": 4.0, "vol24h_usd": 3304701.565487664, "funding_annualized": 0.1095, "venue": "Bitget", "oi_share_pct": 40.8214798246347, "oi_vol_ratio": 2.103010426895972}, {"oi_usd": 2215307.81, "oi_coins": 73843593.66666667, "mark": 0.03, "funding": -1.86e-06, "interval_h": 4.0, "vol24h_usd": 11918151.481839454, "funding_annualized": -0.0040734, "venue": "Binance", "oi_share_pct": 13.012152688672254, "oi_vol_ratio": 0.18587679585845374}, {"oi_usd": 688837.94, "oi_coins": 22961264.666666664, "mark": 0.03, "funding": -3.8e-05, "interval_h": 4.0, "vol24h_usd": 1317736.263452041, "funding_annualized": -0.08322, "venue": "Gate", "oi_share_pct": 4.046058255457717, "oi_vol_ratio": 0.5227434040522405}], "others_oi_usd": 61580819.84, "n_others": 29, "fetched_at": 1780680416, "source": "coingecko"}