{"symbol": "KAS", "total_oi_usd": 16493505.33, "n_venues": 4, "venues": [{"oi_usd": 6799728.38, "oi_coins": 226657612.66666666, "mark": 0.03, "funding": 5e-05, "interval_h": 4.0, "vol24h_usd": 3491724.5439716815, "funding_annualized": 0.1095, "venue": "Bitget", "oi_share_pct": 41.226702535039585, "oi_vol_ratio": 1.9473839629587766}, {"oi_usd": 6768039.33, "oi_coins": 225601311.0, "mark": 0.03, "funding": 5e-05, "interval_h": 4.0, "vol24h_usd": 8172436.2886397345, "funding_annualized": 0.1095, "venue": "Bybit", "oi_share_pct": 41.03457206085615, "oi_vol_ratio": 0.8281544316727258}, {"oi_usd": 2274281.6, "oi_coins": 75809386.66666667, "mark": 0.03, "funding": -2.5679999999999998e-05, "interval_h": 4.0, "vol24h_usd": 13675889.72680032, "funding_annualized": -0.056239199999999996, "venue": "Binance", "oi_share_pct": 13.788952405789171, "oi_vol_ratio": 0.16629862081610264}, {"oi_usd": 651456.02, "oi_coins": 21715200.666666668, "mark": 0.03, "funding": -4e-05, "interval_h": 4.0, "vol24h_usd": 1813024.1231612393, "funding_annualized": -0.08760000000000001, "venue": "Gate", "oi_share_pct": 3.949772998315089, "oi_vol_ratio": 0.35932010593665087}], "others_oi_usd": 61959571.85, "n_others": 29, "fetched_at": 1780728338, "source": "coingecko"}