{"symbol": "M", "total_oi_usd": 60360890.720000006, "n_venues": 4, "venues": [{"oi_usd": 21886025.42, "oi_coins": 7816437.650000001, "mark": 2.8, "funding": 5e-05, "interval_h": 4.0, "vol24h_usd": 1747181.98646962, "funding_annualized": 0.1095, "venue": "Bybit", "oi_share_pct": 36.258619047760796, "oi_vol_ratio": 12.52647153501348}, {"oi_usd": 20880125.94, "oi_coins": 7457187.835714287, "mark": 2.8, "funding": 5e-05, "interval_h": 4.0, "vol24h_usd": 2229128.1449266407, "funding_annualized": 0.1095, "venue": "Binance", "oi_share_pct": 34.59214350705658, "oi_vol_ratio": 9.366947336572773}, {"oi_usd": 11829476.46, "oi_coins": 4224813.021428572, "mark": 2.8, "funding": 9.6e-05, "interval_h": 4.0, "vol24h_usd": 614642.7012617174, "funding_annualized": 0.21024, "venue": "Bitget", "oi_share_pct": 19.597915668398873, "oi_vol_ratio": 19.246102549850278}, {"oi_usd": 5765262.9, "oi_coins": 2059022.4642857146, "mark": 2.8, "funding": 0.0001, "interval_h": 4.0, "vol24h_usd": 242097.66194530937, "funding_annualized": 0.219, "venue": "Gate", "oi_share_pct": 9.551321776783746, "oi_vol_ratio": 23.81379007824698}], "others_oi_usd": 33837446.86, "n_others": 23, "fetched_at": 1781129029, "source": "coingecko"}