{"symbol": "NAORIS", "total_oi_usd": 8587860.09, "n_venues": 4, "venues": [{"oi_usd": 3640356.14, "oi_coins": 91008903.5, "mark": 0.04, "funding": 0.00033047, "interval_h": 4.0, "vol24h_usd": 4476823.084975595, "funding_annualized": 0.7237293, "venue": "Binance", "oi_share_pct": 42.38956040095432, "oi_vol_ratio": 0.813156131234488}, {"oi_usd": 3466362.68, "oi_coins": 86659067.0, "mark": 0.04, "funding": 5e-05, "interval_h": 4.0, "vol24h_usd": 924339.4714418782, "funding_annualized": 0.1095, "venue": "Bitget", "oi_share_pct": 40.36352064044863, "oi_vol_ratio": 3.750097001259523}, {"oi_usd": 1339697.41, "oi_coins": 33492435.249999996, "mark": 0.04, "funding": 5e-05, "interval_h": 4.0, "vol24h_usd": 1555216.820962666, "funding_annualized": 0.1095, "venue": "Bybit", "oi_share_pct": 15.599897948500463, "oi_vol_ratio": 0.8614216306963157}, {"oi_usd": 141443.86, "oi_coins": 3536096.4999999995, "mark": 0.04, "funding": 5e-05, "interval_h": 4.0, "vol24h_usd": 387188.07965298305, "funding_annualized": 0.1095, "venue": "Gate", "oi_share_pct": 1.6470210100965907, "oi_vol_ratio": 0.3653104716621672}], "others_oi_usd": 32159669.87, "n_others": 20, "fetched_at": 1781206662, "source": "coingecko"}