{"symbol": "NAORIS", "total_oi_usd": 6425591.67, "n_venues": 4, "venues": [{"oi_usd": 2704831.33, "oi_coins": 90161044.33333334, "mark": 0.03, "funding": 5e-05, "interval_h": 4.0, "vol24h_usd": 348118.33470518247, "funding_annualized": 0.1095, "venue": "Bitget", "oi_share_pct": 42.094665657458435, "oi_vol_ratio": 7.769861740521916}, {"oi_usd": 2663047.21, "oi_coins": 88768240.33333333, "mark": 0.03, "funding": 5e-05, "interval_h": 4.0, "vol24h_usd": 1863304.6384123028, "funding_annualized": 0.1095, "venue": "Binance", "oi_share_pct": 41.44438904254245, "oi_vol_ratio": 1.4292065586597515}, {"oi_usd": 946619.89, "oi_coins": 31553996.333333336, "mark": 0.03, "funding": 5e-05, "interval_h": 4.0, "vol24h_usd": 641822.6294457329, "funding_annualized": 0.1095, "venue": "Bybit", "oi_share_pct": 14.732026848509658, "oi_vol_ratio": 1.4748932907172263}, {"oi_usd": 111093.24, "oi_coins": 3703108.0000000005, "mark": 0.03, "funding": 5e-05, "interval_h": 4.0, "vol24h_usd": 139152.2236956844, "funding_annualized": 0.1095, "venue": "Gate", "oi_share_pct": 1.7289184514894644, "oi_vol_ratio": 0.7983576334572468}], "others_oi_usd": 32136696.85, "n_others": 20, "fetched_at": 1780757757, "source": "coingecko"}