{"symbol": "PIEVERSE", "total_oi_usd": 21515784.94, "n_venues": 5, "venues": [{"oi_usd": 9353564.05, "oi_coins": 14172066.742424242, "mark": 0.66, "funding": 0.00019716999999999998, "interval_h": 4.0, "vol24h_usd": 8044943.862279556, "funding_annualized": 0.4318023, "venue": "Binance", "oi_share_pct": 43.473031897668704, "oi_vol_ratio": 1.1626636817015208}, {"oi_usd": 5385074.75, "oi_coins": 8159204.166666666, "mark": 0.66, "funding": 5e-05, "interval_h": 4.0, "vol24h_usd": 2689489.153710609, "funding_annualized": 0.1095, "venue": "Bybit", "oi_share_pct": 25.0284838085949, "oi_vol_ratio": 2.0022667660028937}, {"oi_usd": 2498307.84, "oi_coins": 3785314.9090909087, "mark": 0.66, "funding": 5e-05, "interval_h": 4.0, "vol24h_usd": 3728548.0205821483, "funding_annualized": 0.1095, "venue": "OKX", "oi_share_pct": 11.611511487807238, "oi_vol_ratio": 0.6700484548432696}, {"oi_usd": 2381961.91, "oi_coins": 3609033.1969696973, "mark": 0.66, "funding": 0.0001, "interval_h": 4.0, "vol24h_usd": 537227.9497494906, "funding_annualized": 0.219, "venue": "Gate", "oi_share_pct": 11.070764634627363, "oi_vol_ratio": 4.43380116598682}, {"oi_usd": 1896876.39, "oi_coins": 2874055.1363636362, "mark": 0.66, "funding": 0.000169, "interval_h": 4.0, "vol24h_usd": 1092987.8822007577, "funding_annualized": 0.37011, "venue": "Bitget", "oi_share_pct": 8.81620817130179, "oi_vol_ratio": 1.7354962675163361}], "others_oi_usd": 91129329.29, "n_others": 20, "fetched_at": 1781394359, "source": "coingecko"}