{"symbol": "SIREN", "total_oi_usd": 40574262.92, "n_venues": 4, "venues": [{"oi_usd": 23573155.83, "oi_coins": 20147996.435897436, "mark": 1.17, "funding": -0.00057291, "interval_h": 4.0, "vol24h_usd": 359970645.58673745, "funding_annualized": -1.2546729, "venue": "Binance", "oi_share_pct": 58.09879005437272, "oi_vol_ratio": 0.06548632817427853}, {"oi_usd": 7699157.16, "oi_coins": 6524709.4576271195, "mark": 1.18, "funding": -0.00060133, "interval_h": 4.0, "vol24h_usd": 67082537.04364918, "funding_annualized": -1.3169126999999998, "venue": "Bybit", "oi_share_pct": 18.975470177191823, "oi_vol_ratio": 0.11477140697571295}, {"oi_usd": 6588526.95, "oi_coins": 5631219.615384616, "mark": 1.17, "funding": -0.000271, "interval_h": 4.0, "vol24h_usd": 40379669.029555954, "funding_annualized": -0.59349, "venue": "Bitget", "oi_share_pct": 16.238192577867782, "oi_vol_ratio": 0.16316446143175464}, {"oi_usd": 2713422.98, "oi_coins": 2299511.0, "mark": 1.18, "funding": -0.000498, "interval_h": 4.0, "vol24h_usd": 32813494.53280862, "funding_annualized": -1.09062, "venue": "Gate", "oi_share_pct": 6.68754719056767, "oi_vol_ratio": 0.08269228921311567}], "others_oi_usd": 108347128.84, "n_others": 18, "fetched_at": 1780912797, "source": "coingecko"}