{"symbol": "SKYAI", "total_oi_usd": 105836527.2, "n_venues": 3, "venues": [{"oi_usd": 45496563.45, "oi_coins": 168505790.55555555, "mark": 0.27, "funding": 0.000549, "interval_h": 4.0, "vol24h_usd": 13567043.88688318, "funding_annualized": 1.20231, "venue": "Bitget", "oi_share_pct": 42.98758155964891, "oi_vol_ratio": 3.3534618026839844}, {"oi_usd": 31752707.44, "oi_coins": 117602620.14814815, "mark": 0.27, "funding": 0.000523, "interval_h": 4.0, "vol24h_usd": 103858654.1375969, "funding_annualized": 1.14537, "venue": "Binance", "oi_share_pct": 30.00165281311309, "oi_vol_ratio": 0.30573001069253697}, {"oi_usd": 28587256.31, "oi_coins": 105878727.07407406, "mark": 0.27, "funding": 0.000958, "interval_h": 4.0, "vol24h_usd": 17598229.49731795, "funding_annualized": 2.09802, "venue": "Gate", "oi_share_pct": 27.010765627238005, "oi_vol_ratio": 1.624439340011836}], "others_oi_usd": 44033538.24, "n_others": 18, "fetched_at": 1781228586, "source": "coingecko"}