{"symbol": "SKYAI", "total_oi_usd": 65423928.51, "n_venues": 3, "venues": [{"oi_usd": 23399925.63, "oi_coins": 106363298.31818181, "mark": 0.22, "funding": 5e-05, "interval_h": 4.0, "vol24h_usd": 13702752.347480625, "funding_annualized": 0.1095, "venue": "Bitget", "oi_share_pct": 35.766616531477986, "oi_vol_ratio": 1.7076806933829092}, {"oi_usd": 23182791.16, "oi_coins": 105376323.45454545, "mark": 0.22, "funding": 5e-05, "interval_h": 4.0, "vol24h_usd": 66007835.05762547, "funding_annualized": 0.1095, "venue": "Binance", "oi_share_pct": 35.434728069648905, "oi_vol_ratio": 0.3512127180017524}, {"oi_usd": 18841211.72, "oi_coins": 85641871.45454545, "mark": 0.22, "funding": 5e-05, "interval_h": 4.0, "vol24h_usd": 10949640.973786622, "funding_annualized": 0.1095, "venue": "Gate", "oi_share_pct": 28.798655398873112, "oi_vol_ratio": 1.7207150229953432}], "others_oi_usd": 35818156.9, "n_others": 18, "fetched_at": 1780939967, "source": "coingecko"}