{"symbol": "TAG", "total_oi_usd": 14827305.6, "n_venues": 3, "venues": [{"oi_usd": 8070594.67, "oi_coins": null, "mark": 0.0, "funding": 5e-05, "interval_h": 4.0, "vol24h_usd": 4062156.670860722, "funding_annualized": 0.1095, "venue": "Binance", "oi_share_pct": 54.43062204099982, "oi_vol_ratio": 1.9867758247467935}, {"oi_usd": 5624763.92, "oi_coins": null, "mark": 0.0, "funding": 5e-05, "interval_h": 4.0, "vol24h_usd": 1273029.7242823234, "funding_annualized": 0.1095, "venue": "Bitget", "oi_share_pct": 37.93517225408776, "oi_vol_ratio": 4.418407373143614}, {"oi_usd": 1131947.01, "oi_coins": null, "mark": 0.0, "funding": 5e-05, "interval_h": 4.0, "vol24h_usd": 477159.69066049554, "funding_annualized": 0.1095, "venue": "Gate", "oi_share_pct": 7.6342057049124294, "oi_vol_ratio": 2.3722603399988222}], "others_oi_usd": 15124957.53, "n_others": 16, "fetched_at": 1780687505, "source": "coingecko"}