{"symbol": "TAG", "total_oi_usd": 22345189.6, "n_venues": 4, "venues": [{"oi_usd": 9515943.42, "oi_coins": null, "mark": 0.0, "funding": 0.00014659999999999999, "interval_h": 4.0, "vol24h_usd": 2195033.3201495158, "funding_annualized": 0.32105399999999995, "venue": "Binance", "oi_share_pct": 42.586093876777845, "oi_vol_ratio": 4.335215931643268}, {"oi_usd": 6031112.34, "oi_coins": null, "mark": 0.0, "funding": 5e-05, "interval_h": 4.0, "vol24h_usd": 468139.9059726523, "funding_annualized": 0.1095, "venue": "Bitget", "oi_share_pct": 26.99065189404345, "oi_vol_ratio": 12.883140836859834}, {"oi_usd": 5518779.57, "oi_coins": null, "mark": 0.0, "funding": 0.00014800000000000002, "interval_h": 4.0, "vol24h_usd": 196748.20838247144, "funding_annualized": 0.32412, "venue": "MEXC", "oi_share_pct": 24.697841767249987, "oi_vol_ratio": 28.049960990098022}, {"oi_usd": 1279354.27, "oi_coins": null, "mark": 0.0, "funding": 5e-05, "interval_h": 4.0, "vol24h_usd": 456035.6321622564, "funding_annualized": 0.1095, "venue": "Gate", "oi_share_pct": 5.725412461928718, "oi_vol_ratio": 2.8053822547462888}], "fetched_at": 1780472640, "source": "coingecko"}