{"symbol": "UB", "total_oi_usd": 26976335.54, "n_venues": 7, "venues": [{"oi_usd": 9001719.45, "oi_coins": 75014328.75, "mark": 0.12, "funding": 5e-05, "interval_h": 4.0, "vol24h_usd": 91802593.84130843, "funding_annualized": 0.1095, "venue": "Binance", "oi_share_pct": 33.368948264498044, "oi_vol_ratio": 0.09805517549493785}, {"oi_usd": 4383848.45, "oi_coins": 36532070.41666667, "mark": 0.12, "funding": 5e-05, "interval_h": 4.0, "vol24h_usd": 22915653.054662477, "funding_annualized": 0.1095, "venue": "Bitget", "oi_share_pct": 16.250718869876575, "oi_vol_ratio": 0.19130366651750522}, {"oi_usd": 4325934.45, "oi_coins": 36049453.75, "mark": 0.12, "funding": 5e-05, "interval_h": 4.0, "vol24h_usd": 24478743.790877797, "funding_annualized": 0.1095, "venue": "Bybit", "oi_share_pct": 16.036034410921328, "oi_vol_ratio": 0.17672207720120406}, {"oi_usd": 4324323.7, "oi_coins": 39312033.63636364, "mark": 0.11, "funding": -1.85836558656e-05, "interval_h": 4.0, "vol24h_usd": 90114941.54656434, "funding_annualized": -0.040698206345664005, "venue": "OKX", "oi_share_pct": 16.030063436851812, "oi_vol_ratio": 0.047986755867399956}, {"oi_usd": 2616097.64, "oi_coins": 21800813.666666668, "mark": 0.12, "funding": 5e-05, "interval_h": 4.0, "vol24h_usd": 8631112.158069829, "funding_annualized": 0.1095, "venue": "Gate", "oi_share_pct": 9.697750223046048, "oi_vol_ratio": 0.30310087415027137}, {"oi_usd": 2281814.53, "oi_coins": 19015121.083333332, "mark": 0.12, "funding": 5e-05, "interval_h": 4.0, "vol24h_usd": 7483033.028595729, "funding_annualized": 0.1095, "venue": "BingX", "oi_share_pct": 8.45857854420801, "oi_vol_ratio": 0.3049317731567205}, {"oi_usd": 42597.32, "oi_coins": 354977.6666666667, "mark": 0.12, "funding": 5e-05, "interval_h": 4.0, "vol24h_usd": 9317221.927272998, "funding_annualized": 0.1095, "venue": "MEXC", "oi_share_pct": 0.1579062505981863, "oi_vol_ratio": 0.004571890670040909}], "fetched_at": 1780477837, "source": "coingecko"}