{"symbol": "VELVET", "total_oi_usd": 47487599.2, "n_venues": 4, "venues": [{"oi_usd": 26031728.39, "oi_coins": 27991105.795698922, "mark": 0.93, "funding": 0.00061974, "interval_h": 4.0, "vol24h_usd": 1060392505.2561492, "funding_annualized": 1.3572306, "venue": "Binance", "oi_share_pct": 54.81795000914681, "oi_vol_ratio": 0.024549144077278966}, {"oi_usd": 14469064.12, "oi_coins": 15392621.40425532, "mark": 0.94, "funding": 5e-05, "interval_h": 4.0, "vol24h_usd": 49754882.64580652, "funding_annualized": 0.1095, "venue": "Bitget", "oi_share_pct": 30.46914218396621, "oi_vol_ratio": 0.2908069188505963}, {"oi_usd": 5617644.61, "oi_coins": 6241827.344444444, "mark": 0.9, "funding": 5e-05, "interval_h": 4.0, "vol24h_usd": 62310848.78270434, "funding_annualized": 0.1095, "venue": "Bybit", "oi_share_pct": 11.829708607378913, "oi_vol_ratio": 0.0901551610954671}, {"oi_usd": 1369162.08, "oi_coins": 1456555.4042553194, "mark": 0.94, "funding": 0.000104, "interval_h": 4.0, "vol24h_usd": 20557581.182002973, "funding_annualized": 0.22776, "venue": "Gate", "oi_share_pct": 2.8831991995080686, "oi_vol_ratio": 0.06660132181302661}], "others_oi_usd": 78649677.22, "n_others": 15, "fetched_at": 1781135281, "source": "coingecko"}